ishutils/__init__.py
ishutils/common/__init__.py
ishutils/common/confirm.py
ishutils/common/copy.py
ishutils/common/download.py
ishutils/common/extract.py
ishutils/common/link.py
ishutils/common/move.py
ishutils/common/remove.py
ishutils/common/replace.py
ishutils/common/run.py
ishutils/config.py
ishutils/logging.py
ishutils/ubuntu/__init__.py
ishutils/ubuntu/desktop.py
ishutils/utils/text.py
ishutils-0.2.0.dist-info/METADATA
ishutils-0.2.0.dist-info/WHEEL
ishutils-0.2.0.dist-info/LICENSE
ishutils-0.2.0.dist-info/RECORD
